{"dataFrom":"","emptyFlag":false,"errorCode":"0","errorMessage":"处理成功","success":true,"value":{"vtoolsConfig":{"offLineSaleStatus":1,"offLineStopMessage":"抱歉，本彩种已停止销售","onLineSaleStatus":1,"onLineStopMessage":"抱歉，本彩种已停止销售"},"matchInfoList":[{"businessDate":"2026-06-05","subMatchList":[{"awayRank":"","awayTeamAbbEnName":"CHN","awayTeamAbbName":"中国","awayTeamAllName":"中国","awayTeamCode":"CHN","awayTeamId":426,"backColor":"005E5E","baseAwayTeamId":0,"baseHomeTeamId":0,"bettingAllUp":0,"bettingSingle":0,"businessDate":"2026-06-05","crs":{},"groupName":"","had":{"a":"1.56","af":"1","d":"3.90","df":"0","goalLine":"","goalLineValue":"","h":"4.35","hf":"-1","updateDate":"2026-06-05","updateTime":"17:03:40"},"hafu":{},"hhad":{"a":"2.78","af":"1","d":"3.35","df":"0","goalLine":"+1","goalLineValue":"+1.00","h":"2.12","hf":"-1","updateDate":"2026-06-05","updateTime":"17:03:03"},"homeRank":"","homeTeamAbbEnName":"SGP","homeTeamAbbName":"新加坡","homeTeamAllName":"新加坡","homeTeamCode":"SGP","homeTeamId":917,"isHide":0,"isHot":0,"leagueAbbName":"国际赛","leagueAllName":"国际赛","leagueCode":"INT","leagueId":39,"lineNum":"","matchDate":"2026-06-05","matchId":2040114,"matchName":"","matchNum":5201,"matchNumDate":"260605","matchNumStr":"周五201","matchStatus":"Selling","matchTime":"19:30:00","matchWeek":"周五","oddsList":[{"a":"2.780","d":"3.350","goalLine":"+1","goalLineF":"","goalLineValue":"+1.00","h":"2.120","matchId":0,"matchNum":0,"odds":"","poolCode":"HHAD","poolId":2191078,"updateDate":"2026-06-05","updateTime":"17:03:03"},{"a":"1.560","d":"3.900","goalLine":"","goalLineF":"","goalLineValue":"","h":"4.350","matchId":0,"matchNum":0,"odds":"","poolCode":"HAD","poolId":2191053,"updateDate":"2026-06-05","updateTime":"17:03:40"}],"poolList":[{"allUp":1,"bettingAllup":1,"bettingSingle":0,"cbtAllUp":1,"cbtSingle":0,"cbtValue":1,"fixedOddsgoalLine":"","intAllUp":0,"intSingle":0,"intValue":2,"matchId":0,"matchNum":0,"poolCloseDate":"","poolCloseTime":"","poolCode":"HHAD","poolId":2191078,"poolOddsType":"F","poolStatus":"Selling","sellInitialDate":"","sellInitialTime":"","single":0,"updateDate":"","updateTime":"","vbtAllUp":0,"vbtSingle":0,"vbtValue":0},{"allUp":1,"bettingAllup":1,"bettingSingle":1,"cbtAllUp":1,"cbtSingle":1,"cbtValue":1,"fixedOddsgoalLine":"","intAllUp":0,"intSingle":0,"intValue":2,"matchId":0,"matchNum":0,"poolCloseDate":"","poolCloseTime":"","poolCode":"HAD","poolId":2191053,"poolOddsType":"F","poolStatus":"Selling","sellInitialDate":"","sellInitialTime":"","single":1,"updateDate":"","updateTime":"","vbtAllUp":0,"vbtSingle":0,"vbtValue":0}],"remark":"","sellStatus":1,"taxDateNo":"2606051","ttg":{},"vote":{}},{"awayRank":"","awayTeamAbbEnName":"MNG","awayTeamAbbName":"黑山","awayTeamAllName":"黑山","awayTeamCode":"MNG","awayTeamId":885,"backColor":"005E5E","baseAwayTeamId":0,"baseHomeTeamId":0,"bettingAllUp":0,"bettingSingle":0,"businessDate":"2026-06-05","crs":{},"groupName":"","had":{"a":"5.25","af":"1","d":"3.40","df":"0","goalLine":"","goalLineValue":"","h":"1.55","hf":"-1","updateDate":"2026-06-05","updateTime":"17:18:02"},"hafu":{},"hhad":{"a":"2.11","af":"1","d":"3.15","df":"-1","goalLine":"-1","goalLineValue":"-1.00","h":"2.96","hf":"0","updateDate":"2026-06-05","updateTime":"17:18:07"},"homeRank":"","homeTeamAbbEnName":"SVK","homeTeamAbbName":"斯洛伐克","homeTeamAllName":"斯洛伐克","homeTeamCode":"SVK","homeTeamId":541,"isHide":0,"isHot":0,"leagueAbbName":"国际赛","leagueAllName":"国际赛","leagueCode":"INT","leagueId":39,"lineNum":"","matchDate":"2026-06-06","matchId":2040115,"matchName":"","matchNum":5202,"matchNumDate":"260605","matchNumStr":"周五202","matchStatus":"Selling","matchTime":"00:30:00","matchWeek":"周五","oddsList":[{"a":"2.110","d":"3.150","goalLine":"-1","goalLineF":"","goalLineValue":"-1.00","h":"2.960","matchId":0,"matchNum":0,"odds":"","poolCode":"HHAD","poolId":2191082,"updateDate":"2026-06-05","updateTime":"17:18:07"},{"a":"5.250","d":"3.400","goalLine":"","goalLineF":"","goalLineValue":"","h":"1.550","matchId":0,"matchNum":0,"odds":"","poolCode":"HAD","poolId":2191052,"updateDate":"2026-06-05","updateTime":"17:18:02"}],"poolList":[{"allUp":1,"bettingAllup":1,"bettingSingle":0,"cbtAllUp":1,"cbtSingle":0,"cbtValue":1,"fixedOddsgoalLine":"","intAllUp":0,"intSingle":0,"intValue":2,"matchId":0,"matchNum":0,"poolCloseDate":"","poolCloseTime":"","poolCode":"HHAD","poolId":2191082,"poolOddsType":"F","poolStatus":"Selling","sellInitialDate":"","sellInitialTime":"","single":0,"updateDate":"","updateTime":"","vbtAllUp":0,"vbtSingle":0,"vbtValue":0},{"allUp":1,"bettingAllup":1,"bettingSingle":0,"cbtAllUp":1,"cbtSingle":0,"cbtValue":1,"fixedOddsgoalLine":"","intAllUp":0,"intSingle":0,"intValue":2,"matchId":0,"matchNum":0,"poolCloseDate":"","poolCloseTime":"","poolCode":"HAD","poolId":2191052,"poolOddsType":"F","poolStatus":"Selling","sellInitialDate":"","sellInitialTime":"","single":0,"updateDate":"","updateTime":"","vbtAllUp":0,"vbtSingle":0,"vbtValue":0}],"remark":"","sellStatus":1,"taxDateNo":"2606051","ttg":{},"vote":{}},{"awayRank":"","awayTeamAbbEnName":"FIN","awayTeamAbbName":"芬兰","awayTeamAllName":"芬兰","awayTeamCode":"FIN","awayTeamId":374,"backColor":"005E5E","baseAwayTeamId":0,"baseHomeTeamId":0,"bettingAllUp":0,"bettingSingle":0,"businessDate":"2026-06-05","crs":{},"groupName":"","had":{"a":"6.10","af":"0","d":"3.85","df":"0","goalLine":"","goalLineValue":"","h":"1.42","hf":"0","updateDate":"2026-06-05","updateTime":"13:12:53"},"hafu":{},"hhad":{"a":"2.45","af":"0","d":"3.14","df":"0","goalLine":"-1","goalLineValue":"-1.00","h":"2.48","hf":"0","updateDate":"2026-06-05","updateTime":"13:13:01"},"homeRank":"","homeTeamAbbEnName":"HUN","homeTeamAbbName":"匈牙利","homeTeamAllName":"匈牙利","homeTeamCode":"HUN","homeTeamId":379,"isHide":0,"isHot":0,"leagueAbbName":"国际赛","leagueAllName":"国际赛","leagueCode":"INT","leagueId":39,"lineNum":"","matchDate":"2026-06-06","matchId":2040116,"matchName":"","matchNum":5203,"matchNumDate":"260605","matchNumStr":"周五203","matchStatus":"Selling","matchTime":"01:45:00","matchWeek":"周五","oddsList":[{"a":"2.450","d":"3.140","goalLine":"-1","goalLineF":"","goalLineValue":"-1.00","h":"2.480","matchId":0,"matchNum":0,"odds":"","poolCode":"HHAD","poolId":2191088,"updateDate":"2026-06-05","updateTime":"13:13:01"},{"a":"6.100","d":"3.850","goalLine":"","goalLineF":"","goalLineValue":"","h":"1.420","matchId":0,"matchNum":0,"odds":"","poolCode":"HAD","poolId":2191061,"updateDate":"2026-06-05","updateTime":"13:12:53"}],"poolList":[{"allUp":1,"bettingAllup":1,"bettingSingle":0,"cbtAllUp":1,"cbtSingle":0,"cbtValue":1,"fixedOddsgoalLine":"","intAllUp":0,"intSingle":0,"intValue":2,"matchId":0,"matchNum":0,"poolCloseDate":"","poolCloseTime":"","poolCode":"HHAD","poolId":2191088,"poolOddsType":"F","poolStatus":"Selling","sellInitialDate":"","sellInitialTime":"","single":0,"updateDate":"","updateTime":"","vbtAllUp":0,"vbtSingle":0,"vbtValue":0},{"allUp":1,"bettingAllup":1,"bettingSingle":0,"cbtAllUp":1,"cbtSingle":0,"cbtValue":1,"fixedOddsgoalLine":"","intAllUp":0,"intSingle":0,"intValue":2,"matchId":0,"matchNum":0,"poolCloseDate":"","poolCloseTime":"","poolCode":"HAD","poolId":2191061,"poolOddsType":"F","poolStatus":"Selling","sellInitialDate":"","sellInitialTime":"","single":0,"updateDate":"","updateTime":"","vbtAllUp":0,"vbtSingle":0,"vbtValue":0}],"remark":"","sellStatus":1,"taxDateNo":"2606051","ttg":{},"vote":{}},{"awayRank":"","awayTeamAbbEnName":"IRE","awayTeamAbbName":"爱尔兰","awayTeamAllName":"爱尔兰","awayTeamCode":"IRE","awayTeamId":394,"backColor":"005E5E","baseAwayTeamId":0,"baseHomeTeamId":0,"bettingAllUp":0,"bettingSingle":0,"businessDate":"2026-06-05","crs":{},"groupName":"","had":{"a":"5.65","af":"0","d":"3.80","df":"0","goalLine":"","goalLineValue":"","h":"1.45","hf":"0","updateDate":"2026-06-05","updateTime":"13:50:15"},"hafu":{},"hhad":{"a":"2.36","af":"0","d":"3.20","df":"0","goalLine":"-1","goalLineValue":"-1.00","h":"2.55","hf":"0","updateDate":"2026-06-05","updateTime":"13:50:22"},"homeRank":"","homeTeamAbbEnName":"CAA","homeTeamAbbName":"加拿大","homeTeamAllName":"加拿大","homeTeamCode":"CAA","homeTeamId":542,"isHide":0,"isHot":0,"leagueAbbName":"国际赛","leagueAllName":"国际赛","leagueCode":"INT","leagueId":39,"lineNum":"","matchDate":"2026-06-06","matchId":2040117,"matchName":"","matchNum":5204,"matchNumDate":"260605","matchNumStr":"周五204","matchStatus":"Selling","matchTime":"07:30:00","matchWeek":"周五","oddsList":[{"a":"2.360","d":"3.200","goalLine":"-1","goalLineF":"","goalLineValue":"-1.00","h":"2.550","matchId":0,"matchNum":0,"odds":"","poolCode":"HHAD","poolId":2191042,"updateDate":"2026-06-05","updateTime":"13:50:22"},{"a":"5.650","d":"3.800","goalLine":"","goalLineF":"","goalLineValue":"","h":"1.450","matchId":0,"matchNum":0,"odds":"","poolCode":"HAD","poolId":2191065,"updateDate":"2026-06-05","updateTime":"13:50:15"}],"poolList":[{"allUp":1,"bettingAllup":1,"bettingSingle":0,"cbtAllUp":1,"cbtSingle":0,"cbtValue":1,"fixedOddsgoalLine":"","intAllUp":0,"intSingle":0,"intValue":2,"matchId":0,"matchNum":0,"poolCloseDate":"","poolCloseTime":"","poolCode":"HHAD","poolId":2191042,"poolOddsType":"F","poolStatus":"Selling","sellInitialDate":"","sellInitialTime":"","single":0,"updateDate":"","updateTime":"","vbtAllUp":0,"vbtSingle":0,"vbtValue":0},{"allUp":1,"bettingAllup":1,"bettingSingle":0,"cbtAllUp":1,"cbtSingle":0,"cbtValue":1,"fixedOddsgoalLine":"","intAllUp":0,"intSingle":0,"intValue":2,"matchId":0,"matchNum":0,"poolCloseDate":"","poolCloseTime":"","poolCode":"HAD","poolId":2191065,"poolOddsType":"F","poolStatus":"Selling","sellInitialDate":"","sellInitialTime":"","single":0,"updateDate":"","updateTime":"","vbtAllUp":0,"vbtSingle":0,"vbtValue":0}],"remark":"","sellStatus":1,"taxDateNo":"2606051","ttg":{},"vote":{}}],"weekday":"周五","matchCount":4,"matchNumDate":"260605"},{"businessDate":"2026-06-06","subMatchList":[{"awayRank":"[日职1]","awayTeamAbbEnName":"VIS","awayTeamAbbName":"神户胜利","awayTeamAllName":"神户胜利船","awayTeamCode":"VIS","awayTeamId":561,"backColor":"009900","baseAwayTeamId":0,"baseHomeTeamId":0,"bettingAllUp":0,"bettingSingle":0,"businessDate":"2026-06-06","crs":{},"groupName":"","had":{"a":"2.92","af":"0","d":"3.20","df":"0","goalLine":"","goalLineValue":"","h":"2.11","hf":"0","updateDate":"2026-06-05","updateTime":"09:25:41"},"hafu":{},"hhad":{"a":"1.55","af":"0","d":"3.65","df":"0","goalLine":"-1","goalLineValue":"-1.00","h":"4.80","hf":"0","updateDate":"2026-06-05","updateTime":"09:25:41"},"homeRank":"[日职1]","homeTeamAbbEnName":"KAS","homeTeamAbbName":"鹿岛鹿角","homeTeamAllName":"鹿岛鹿角","homeTeamCode":"KAS","homeTeamId":551,"isHide":0,"isHot":0,"leagueAbbName":"日职","leagueAllName":"日本职业联赛","leagueCode":"JD1","leagueId":42,"lineNum":"","matchDate":"2026-06-06","matchId":2040124,"matchName":"","matchNum":6201,"matchNumDate":"260606","matchNumStr":"周六201","matchStatus":"Selling","matchTime":"13:00:00","matchWeek":"周六","oddsList":[{"a":"1.550","d":"3.650","goalLine":"-1","goalLineF":"","goalLineValue":"-1.00","h":"4.800","matchId":0,"matchNum":0,"odds":"","poolCode":"HHAD","poolId":2191077,"updateDate":"2026-06-05","updateTime":"09:25:41"},{"a":"2.920","d":"3.200","goalLine":"","goalLineF":"","goalLineValue":"","h":"2.110","matchId":0,"matchNum":0,"odds":"","poolCode":"HAD","poolId":2191064,"updateDate":"2026-06-05","updateTime":"09:25:41"}],"poolList":[{"allUp":1,"bettingAllup":1,"bettingSingle":0,"cbtAllUp":1,"cbtSingle":0,"cbtValue":1,"fixedOddsgoalLine":"","intAllUp":0,"intSingle":0,"intValue":2,"matchId":0,"matchNum":0,"poolCloseDate":"","poolCloseTime":"","poolCode":"HHAD","poolId":2191077,"poolOddsType":"F","poolStatus":"Selling","sellInitialDate":"","sellInitialTime":"","single":0,"updateDate":"","updateTime":"","vbtAllUp":0,"vbtSingle":0,"vbtValue":0},{"allUp":1,"bettingAllup":1,"bettingSingle":0,"cbtAllUp":1,"cbtSingle":0,"cbtValue":1,"fixedOddsgoalLine":"","intAllUp":0,"intSingle":0,"intValue":2,"matchId":0,"matchNum":0,"poolCloseDate":"","poolCloseTime":"","poolCode":"HAD","poolId":2191064,"poolOddsType":"F","poolStatus":"Selling","sellInitialDate":"","sellInitialTime":"","single":0,"updateDate":"","updateTime":"","vbtAllUp":0,"vbtSingle":0,"vbtValue":0}],"remark":"","sellStatus":1,"taxDateNo":"2606061","ttg":{},"vote":{}},{"awayRank":"[日职3]","awayTeamAbbEnName":"NAG","awayTeamAbbName":"名古屋鲸","awayTeamAllName":"名古屋鲸八","awayTeamCode":"NAG","awayTeamId":554,"backColor":"009900","baseAwayTeamId":0,"baseHomeTeamId":0,"bettingAllUp":0,"bettingSingle":0,"businessDate":"2026-06-06","crs":{},"groupName":"","had":{"a":"3.30","af":"0","d":"3.25","df":"0","goalLine":"","goalLineValue":"","h":"1.93","hf":"0","updateDate":"2026-06-05","updateTime":"09:25:41"},"hafu":{},"hhad":{"a":"1.66","af":"0","d":"3.55","df":"0","goalLine":"-1","goalLineValue":"-1.00","h":"4.10","hf":"0","updateDate":"2026-06-05","updateTime":"09:25:41"},"homeRank":"[日职3]","homeTeamAbbEnName":"MCZ","homeTeamAbbName":"町田泽维","homeTeamAllName":"町田泽维亚","homeTeamCode":"MCZ","homeTeamId":1489,"isHide":0,"isHot":0,"leagueAbbName":"日职","leagueAllName":"日本职业联赛","leagueCode":"JD1","leagueId":42,"lineNum":"","matchDate":"2026-06-06","matchId":2040125,"matchName":"","matchNum":6202,"matchNumDate":"260606","matchNumStr":"周六202","matchStatus":"Selling","matchTime":"14:00:00","matchWeek":"周六","oddsList":[{"a":"1.660","d":"3.550","goalLine":"-1","goalLineF":"","goalLineValue":"-1.00","h":"4.100","matchId":0,"matchNum":0,"odds":"","poolCode":"HHAD","poolId":2191083,"updateDate":"2026-06-05","updateTime":"09:25:41"},{"a":"3.300","d":"3.250","goalLine":"","goalLineF":"","goalLineValue":"","h":"1.930","matchId":0,"matchNum":0,"odds":"","poolCode":"HAD","poolId":2191054,"updateDate":"2026-06-05","updateTime":"09:25:41"}],"poolList":[{"allUp":1,"bettingAllup":1,"bettingSingle":0,"cbtAllUp":1,"cbtSingle":0,"cbtValue":1,"fixedOddsgoalLine":"","intAllUp":0,"intSingle":0,"intValue":2,"matchId":0,"matchNum":0,"poolCloseDate":"","poolCloseTime":"","poolCode":"HHAD","poolId":2191083,"poolOddsType":"F","poolStatus":"Selling","sellInitialDate":"","sellInitialTime":"","single":0,"updateDate":"","updateTime":"","vbtAllUp":0,"vbtSingle":0,"vbtValue":0},{"allUp":1,"bettingAllup":1,"bettingSingle":0,"cbtAllUp":1,"cbtSingle":0,"cbtValue":1,"fixedOddsgoalLine":"","intAllUp":0,"intSingle":0,"intValue":2,"matchId":0,"matchNum":0,"poolCloseDate":"","poolCloseTime":"","poolCode":"HAD","poolId":2191054,"poolOddsType":"F","poolStatus":"Selling","sellInitialDate":"","sellInitialTime":"","single":0,"updateDate":"","updateTime":"","vbtAllUp":0,"vbtSingle":0,"vbtValue":0}],"remark":"","sellStatus":1,"taxDateNo":"2606061","ttg":{},"vote":{}},{"awayRank":"[日职6]","awayTeamAbbEnName":"OKY","awayTeamAbbName":"冈山绿雉","awayTeamAllName":"冈山绿雉","awayTeamCode":"OKY","awayTeamId":1194,"backColor":"009900","baseAwayTeamId":0,"baseHomeTeamId":0,"bettingAllUp":0,"bettingSingle":0,"businessDate":"2026-06-06","crs":{},"groupName":"","had":{"a":"3.62","af":"0","d":"3.15","df":"0","goalLine":"","goalLineValue":"","h":"1.87","hf":"0","updateDate":"2026-06-05","updateTime":"09:25:41"},"hafu":{},"hhad":{"a":"1.72","af":"0","d":"3.35","df":"0","goalLine":"-1","goalLineValue":"-1.00","h":"4.00","hf":"0","updateDate":"2026-06-05","updateTime":"09:25:41"},"homeRank":"[日职6]","homeTeamAbbEnName":"URA","homeTeamAbbName":"浦和红钻","homeTeamAllName":"浦和红钻","homeTeamCode":"URA","homeTeamId":560,"isHide":0,"isHot":0,"leagueAbbName":"日职","leagueAllName":"日本职业联赛","leagueCode":"JD1","leagueId":42,"lineNum":"","matchDate":"2026-06-06","matchId":2040126,"matchName":"","matchNum":6203,"matchNumDate":"260606","matchNumStr":"周六203","matchStatus":"Selling","matchTime":"15:00:00","matchWeek":"周六","oddsList":[{"a":"1.720","d":"3.350","goalLine":"-1","goalLineF":"","goalLineValue":"-1.00","h":"4.000","matchId":0,"matchNum":0,"odds":"","poolCode":"HHAD","poolId":2191046,"updateDate":"2026-06-05","updateTime":"09:25:41"},{"a":"3.620","d":"3.150","goalLine":"","goalLineF":"","goalLineValue":"","h":"1.870","matchId":0,"matchNum":0,"odds":"","poolCode":"HAD","poolId":2191075,"updateDate":"2026-06-05","updateTime":"09:25:41"}],"poolList":[{"allUp":1,"bettingAllup":1,"bettingSingle":0,"cbtAllUp":1,"cbtSingle":0,"cbtValue":1,"fixedOddsgoalLine":"","intAllUp":0,"intSingle":0,"intValue":2,"matchId":0,"matchNum":0,"poolCloseDate":"","poolCloseTime":"","poolCode":"HHAD","poolId":2191046,"poolOddsType":"F","poolStatus":"Selling","sellInitialDate":"","sellInitialTime":"","single":0,"updateDate":"","updateTime":"","vbtAllUp":0,"vbtSingle":0,"vbtValue":0},{"allUp":1,"bettingAllup":1,"bettingSingle":0,"cbtAllUp":1,"cbtSingle":0,"cbtValue":1,"fixedOddsgoalLine":"","intAllUp":0,"intSingle":0,"intValue":2,"matchId":0,"matchNum":0,"poolCloseDate":"","poolCloseTime":"","poolCode":"HAD","poolId":2191075,"poolOddsType":"F","poolStatus":"Selling","sellInitialDate":"","sellInitialTime":"","single":0,"updateDate":"","updateTime":"","vbtAllUp":0,"vbtSingle":0,"vbtValue":0}],"remark":"","sellStatus":1,"taxDateNo":"2606061","ttg":{},"vote":{}},{"awayRank":"[日职7]","awayTeamAbbEnName":"SHI","awayTeamAbbName":"清水鼓动","awayTeamAllName":"清水鼓动","awayTeamCode":"SHI","awayTeamId":558,"backColor":"009900","baseAwayTeamId":0,"baseHomeTeamId":0,"bettingAllUp":0,"bettingSingle":0,"businessDate":"2026-06-06","crs":{},"groupName":"","had":{"a":"2.96","af":"0","d":"3.20","df":"0","goalLine":"","goalLineValue":"","h":"2.09","hf":"0","updateDate":"2026-06-05","updateTime":"09:25:41"},"hafu":{},"hhad":{"a":"1.56","af":"0","d":"3.65","df":"0","goalLine":"-1","goalLineValue":"-1.00","h":"4.70","hf":"0","updateDate":"2026-06-05","updateTime":"09:25:41"},"homeRank":"[日职7]","homeTeamAbbEnName":"YOK","homeTeamAbbName":"横滨水手","homeTeamAllName":"横滨水手","homeTeamCode":"YOK","homeTeamId":562,"isHide":0,"isHot":0,"leagueAbbName":"日职","leagueAllName":"日本职业联赛","leagueCode":"JD1","leagueId":42,"lineNum":"","matchDate":"2026-06-06","matchId":2040127,"matchName":"","matchNum":6204,"matchNumDate":"260606","matchNumStr":"周六204","matchStatus":"Selling","matchTime":"16:00:00","matchWeek":"周六","oddsList":[{"a":"1.560","d":"3.650","goalLine":"-1","goalLineF":"","goalLineValue":"-1.00","h":"4.700","matchId":0,"matchNum":0,"odds":"","poolCode":"HHAD","poolId":2191044,"updateDate":"2026-06-05","updateTime":"09:25:41"},{"a":"2.960","d":"3.200","goalLine":"","goalLineF":"","goalLineValue":"","h":"2.090","matchId":0,"matchNum":0,"odds":"","poolCode":"HAD","poolId":2191066,"updateDate":"2026-06-05","updateTime":"09:25:41"}],"poolList":[{"allUp":1,"bettingAllup":1,"bettingSingle":0,"cbtAllUp":1,"cbtSingle":0,"cbtValue":1,"fixedOddsgoalLine":"","intAllUp":0,"intSingle":0,"intValue":2,"matchId":0,"matchNum":0,"poolCloseDate":"","poolCloseTime":"","poolCode":"HHAD","poolId":2191044,"poolOddsType":"F","poolStatus":"Selling","sellInitialDate":"","sellInitialTime":"","single":0,"updateDate":"","updateTime":"","vbtAllUp":0,"vbtSingle":0,"vbtValue":0},{"allUp":1,"bettingAllup":1,"bettingSingle":0,"cbtAllUp":1,"cbtSingle":0,"cbtValue":1,"fixedOddsgoalLine":"","intAllUp":0,"intSingle":0,"intValue":2,"matchId":0,"matchNum":0,"poolCloseDate":"","poolCloseTime":"","poolCode":"HAD","poolId":2191066,"poolOddsType":"F","poolStatus":"Selling","sellInitialDate":"","sellInitialTime":"","single":0,"updateDate":"","updateTime":"","vbtAllUp":0,"vbtSingle":0,"vbtValue":0}],"remark":"","sellStatus":1,"taxDateNo":"2606061","ttg":{},"vote":{}},{"awayRank":"[日职8]","awayTeamAbbEnName":"KPS","awayTeamAbbName":"京都","awayTeamAllName":"京都不死鸟","awayTeamCode":"KPS","awayTeamId":785,"backColor":"009900","baseAwayTeamId":0,"baseHomeTeamId":0,"bettingAllUp":0,"bettingSingle":0,"businessDate":"2026-06-06","crs":{},"groupName":"","had":{"a":"3.56","af":"0","d":"3.45","df":"0","goalLine":"","goalLineValue":"","h":"1.79","hf":"0","updateDate":"2026-06-05","updateTime":"09:25:41"},"hafu":{},"hhad":{"a":"1.79","af":"0","d":"3.45","df":"0","goalLine":"-1","goalLineValue":"-1.00","h":"3.57","hf":"0","updateDate":"2026-06-05","updateTime":"09:25:41"},"homeRank":"[日职8]","homeTeamAbbEnName":"KAH","homeTeamAbbName":"柏太阳神","homeTeamAllName":"柏太阳神","homeTeamCode":"KAH","homeTeamId":552,"isHide":0,"isHot":0,"leagueAbbName":"日职","leagueAllName":"日本职业联赛","leagueCode":"JD1","leagueId":42,"lineNum":"","matchDate":"2026-06-06","matchId":2040128,"matchName":"","matchNum":6205,"matchNumDate":"260606","matchNumStr":"周六205","matchStatus":"Selling","matchTime":"17:00:00","matchWeek":"周六","oddsList":[{"a":"1.790","d":"3.450","goalLine":"-1","goalLineF":"","goalLineValue":"-1.00","h":"3.570","matchId":0,"matchNum":0,"odds":"","poolCode":"HHAD","poolId":2191060,"updateDate":"2026-06-05","updateTime":"09:25:41"},{"a":"3.560","d":"3.450","goalLine":"","goalLineF":"","goalLineValue":"","h":"1.790","matchId":0,"matchNum":0,"odds":"","poolCode":"HAD","poolId":2191085,"updateDate":"2026-06-05","updateTime":"09:25:41"}],"poolList":[{"allUp":1,"bettingAllup":1,"bettingSingle":0,"cbtAllUp":1,"cbtSingle":0,"cbtValue":1,"fixedOddsgoalLine":"","intAllUp":0,"intSingle":0,"intValue":2,"matchId":0,"matchNum":0,"poolCloseDate":"","poolCloseTime":"","poolCode":"HHAD","poolId":2191060,"poolOddsType":"F","poolStatus":"Selling","sellInitialDate":"","sellInitialTime":"","single":0,"updateDate":"","updateTime":"","vbtAllUp":0,"vbtSingle":0,"vbtValue":0},{"allUp":1,"bettingAllup":1,"bettingSingle":0,"cbtAllUp":1,"cbtSingle":0,"cbtValue":1,"fixedOddsgoalLine":"","intAllUp":0,"intSingle":0,"intValue":2,"matchId":0,"matchNum":0,"poolCloseDate":"","poolCloseTime":"","poolCode":"HAD","poolId":2191085,"poolOddsType":"F","poolStatus":"Selling","sellInitialDate":"","sellInitialTime":"","single":0,"updateDate":"","updateTime":"","vbtAllUp":0,"vbtSingle":0,"vbtValue":0}],"remark":"","sellStatus":1,"taxDateNo":"2606061","ttg":{},"vote":{}},{"awayRank":"[日职4]","awayTeamAbbEnName":"SAN","awayTeamAbbName":"广岛三箭","awayTeamAllName":"广岛三箭","awayTeamCode":"SAN","awayTeamId":557,"backColor":"009900","baseAwayTeamId":0,"baseHomeTeamId":0,"bettingAllUp":0,"bettingSingle":0,"businessDate":"2026-06-06","crs":{},"groupName":"","had":{"a":"1.89","af":"0","d":"3.60","df":"0","goalLine":"","goalLineValue":"","h":"3.10","hf":"0","updateDate":"2026-06-05","updateTime":"09:25:41"},"hafu":{},"hhad":{"a":"3.70","af":"0","d":"3.70","df":"0","goalLine":"+1","goalLineValue":"+1.00","h":"1.70","hf":"0","updateDate":"2026-06-05","updateTime":"09:25:41"},"homeRank":"[日职4]","homeTeamAbbEnName":"KAW","homeTeamAbbName":"川崎前锋","homeTeamAllName":"川崎前锋","homeTeamCode":"KAW","homeTeamId":553,"isHide":0,"isHot":0,"leagueAbbName":"日职","leagueAllName":"日本职业联赛","leagueCode":"JD1","leagueId":42,"lineNum":"","matchDate":"2026-06-06","matchId":2040129,"matchName":"","matchNum":6206,"matchNumDate":"260606","matchNumStr":"周六206","matchStatus":"Selling","matchTime":"18:00:00","matchWeek":"周六","oddsList":[{"a":"3.700","d":"3.700","goalLine":"+1","goalLineF":"","goalLineValue":"+1.00","h":"1.700","matchId":0,"matchNum":0,"odds":"","poolCode":"HHAD","poolId":2191048,"updateDate":"2026-06-05","updateTime":"09:25:41"},{"a":"1.890","d":"3.600","goalLine":"","goalLineF":"","goalLineValue":"","h":"3.100","matchId":0,"matchNum":0,"odds":"","poolCode":"HAD","poolId":2191079,"updateDate":"2026-06-05","updateTime":"09:25:41"}],"poolList":[{"allUp":1,"bettingAllup":1,"bettingSingle":0,"cbtAllUp":1,"cbtSingle":0,"cbtValue":1,"fixedOddsgoalLine":"","intAllUp":0,"intSingle":0,"intValue":2,"matchId":0,"matchNum":0,"poolCloseDate":"","poolCloseTime":"","poolCode":"HHAD","poolId":2191048,"poolOddsType":"F","poolStatus":"Selling","sellInitialDate":"","sellInitialTime":"","single":0,"updateDate":"","updateTime":"","vbtAllUp":0,"vbtSingle":0,"vbtValue":0},{"allUp":1,"bettingAllup":1,"bettingSingle":0,"cbtAllUp":1,"cbtSingle":0,"cbtValue":1,"fixedOddsgoalLine":"","intAllUp":0,"intSingle":0,"intValue":2,"matchId":0,"matchNum":0,"poolCloseDate":"","poolCloseTime":"","poolCode":"HAD","poolId":2191079,"poolOddsType":"F","poolStatus":"Selling","sellInitialDate":"","sellInitialTime":"","single":0,"updateDate":"","updateTime":"","vbtAllUp":0,"vbtSingle":0,"vbtValue":0}],"remark":"","sellStatus":1,"taxDateNo":"2606061","ttg":{},"vote":{}}],"weekday":"周六","matchCount":6,"matchNumDate":"260606"}],"matchDateList":[{"businessDate":"2026-06-05","businessDateCn":"周五","matchDate":"","matchDateCn":""},{"businessDate":"2026-06-06","businessDateCn":"周六","matchDate":"","matchDateCn":""}],"allUpList":{"HHAD":[{"fValue":1,"formula":"2x1","formulaType":1,"maxMatchCount":0,"poolCode":"HHAD"},{"fValue":1,"formula":"3x1","formulaType":1,"maxMatchCount":0,"poolCode":"HHAD"},{"fValue":1,"formula":"3x3","formulaType":1,"maxMatchCount":0,"poolCode":"HHAD"},{"fValue":1,"formula":"3x4","formulaType":1,"maxMatchCount":0,"poolCode":"HHAD"},{"fValue":1,"formula":"4x1","formulaType":1,"maxMatchCount":0,"poolCode":"HHAD"},{"fValue":1,"formula":"4x4","formulaType":1,"maxMatchCount":0,"poolCode":"HHAD"},{"fValue":1,"formula":"4x5","formulaType":1,"maxMatchCount":0,"poolCode":"HHAD"},{"fValue":1,"formula":"4x6","formulaType":1,"maxMatchCount":0,"poolCode":"HHAD"},{"fValue":1,"formula":"4x11","formulaType":1,"maxMatchCount":0,"poolCode":"HHAD"},{"fValue":1,"formula":"5x1","formulaType":1,"maxMatchCount":0,"poolCode":"HHAD"},{"fValue":1,"formula":"5x5","formulaType":1,"maxMatchCount":0,"poolCode":"HHAD"},{"fValue":1,"formula":"5x6","formulaType":1,"maxMatchCount":0,"poolCode":"HHAD"},{"fValue":1,"formula":"5x10","formulaType":1,"maxMatchCount":0,"poolCode":"HHAD"},{"fValue":1,"formula":"5x16","formulaType":1,"maxMatchCount":0,"poolCode":"HHAD"},{"fValue":1,"formula":"5x20","formulaType":1,"maxMatchCount":0,"poolCode":"HHAD"},{"fValue":1,"formula":"5x26","formulaType":1,"maxMatchCount":0,"poolCode":"HHAD"},{"fValue":1,"formula":"6x1","formulaType":1,"maxMatchCount":0,"poolCode":"HHAD"},{"fValue":1,"formula":"6x6","formulaType":1,"maxMatchCount":0,"poolCode":"HHAD"},{"fValue":1,"formula":"6x7","formulaType":1,"maxMatchCount":0,"poolCode":"HHAD"},{"fValue":1,"formula":"6x15","formulaType":1,"maxMatchCount":0,"poolCode":"HHAD"},{"fValue":1,"formula":"6x20","formulaType":1,"maxMatchCount":0,"poolCode":"HHAD"},{"fValue":1,"formula":"6x22","formulaType":1,"maxMatchCount":0,"poolCode":"HHAD"},{"fValue":1,"formula":"6x35","formulaType":1,"maxMatchCount":0,"poolCode":"HHAD"},{"fValue":1,"formula":"6x42","formulaType":1,"maxMatchCount":0,"poolCode":"HHAD"},{"fValue":1,"formula":"6x50","formulaType":1,"maxMatchCount":0,"poolCode":"HHAD"},{"fValue":1,"formula":"6x57","formulaType":1,"maxMatchCount":0,"poolCode":"HHAD"},{"fValue":1,"formula":"7x1","formulaType":1,"maxMatchCount":0,"poolCode":"HHAD"},{"fValue":1,"formula":"7x7","formulaType":1,"maxMatchCount":0,"poolCode":"HHAD"},{"fValue":1,"formula":"7x8","formulaType":1,"maxMatchCount":0,"poolCode":"HHAD"},{"fValue":1,"formula":"7x21","formulaType":1,"maxMatchCount":0,"poolCode":"HHAD"},{"fValue":1,"formula":"7x35","formulaType":1,"maxMatchCount":0,"poolCode":"HHAD"},{"fValue":1,"formula":"7x120","formulaType":1,"maxMatchCount":0,"poolCode":"HHAD"},{"fValue":1,"formula":"8x1","formulaType":1,"maxMatchCount":0,"poolCode":"HHAD"},{"fValue":1,"formula":"8x8","formulaType":1,"maxMatchCount":0,"poolCode":"HHAD"},{"fValue":1,"formula":"8x9","formulaType":1,"maxMatchCount":0,"poolCode":"HHAD"},{"fValue":1,"formula":"8x28","formulaType":1,"maxMatchCount":0,"poolCode":"HHAD"},{"fValue":1,"formula":"8x56","formulaType":1,"maxMatchCount":0,"poolCode":"HHAD"},{"fValue":1,"formula":"8x70","formulaType":1,"maxMatchCount":0,"poolCode":"HHAD"},{"fValue":1,"formula":"8x247","formulaType":1,"maxMatchCount":0,"poolCode":"HHAD"},{"fValue":1,"formula":"Single","formulaType":1,"maxMatchCount":0,"poolCode":"HHAD"},{"fValue":1,"formula":"2x1","formulaType":2,"maxMatchCount":0,"poolCode":"HHAD"},{"fValue":1,"formula":"3x1","formulaType":2,"maxMatchCount":0,"poolCode":"HHAD"},{"fValue":1,"formula":"4x1","formulaType":2,"maxMatchCount":0,"poolCode":"HHAD"},{"fValue":1,"formula":"5x1","formulaType":2,"maxMatchCount":0,"poolCode":"HHAD"},{"fValue":1,"formula":"6x1","formulaType":2,"maxMatchCount":0,"poolCode":"HHAD"},{"fValue":1,"formula":"7x1","formulaType":2,"maxMatchCount":0,"poolCode":"HHAD"},{"fValue":1,"formula":"8x1","formulaType":2,"maxMatchCount":0,"poolCode":"HHAD"},{"fValue":1,"formula":"Single","formulaType":2,"maxMatchCount":0,"poolCode":"HHAD"}],"HAD":[{"fValue":1,"formula":"2x1","formulaType":1,"maxMatchCount":0,"poolCode":"HAD"},{"fValue":1,"formula":"3x1","formulaType":1,"maxMatchCount":0,"poolCode":"HAD"},{"fValue":1,"formula":"3x3","formulaType":1,"maxMatchCount":0,"poolCode":"HAD"},{"fValue":1,"formula":"3x4","formulaType":1,"maxMatchCount":0,"poolCode":"HAD"},{"fValue":1,"formula":"4x1","formulaType":1,"maxMatchCount":0,"poolCode":"HAD"},{"fValue":1,"formula":"4x4","formulaType":1,"maxMatchCount":0,"poolCode":"HAD"},{"fValue":1,"formula":"4x5","formulaType":1,"maxMatchCount":0,"poolCode":"HAD"},{"fValue":1,"formula":"4x6","formulaType":1,"maxMatchCount":0,"poolCode":"HAD"},{"fValue":1,"formula":"4x11","formulaType":1,"maxMatchCount":0,"poolCode":"HAD"},{"fValue":1,"formula":"5x1","formulaType":1,"maxMatchCount":0,"poolCode":"HAD"},{"fValue":1,"formula":"5x5","formulaType":1,"maxMatchCount":0,"poolCode":"HAD"},{"fValue":1,"formula":"5x6","formulaType":1,"maxMatchCount":0,"poolCode":"HAD"},{"fValue":1,"formula":"5x10","formulaType":1,"maxMatchCount":0,"poolCode":"HAD"},{"fValue":1,"formula":"5x16","formulaType":1,"maxMatchCount":0,"poolCode":"HAD"},{"fValue":1,"formula":"5x20","formulaType":1,"maxMatchCount":0,"poolCode":"HAD"},{"fValue":1,"formula":"5x26","formulaType":1,"maxMatchCount":0,"poolCode":"HAD"},{"fValue":1,"formula":"6x1","formulaType":1,"maxMatchCount":0,"poolCode":"HAD"},{"fValue":1,"formula":"6x6","formulaType":1,"maxMatchCount":0,"poolCode":"HAD"},{"fValue":1,"formula":"6x7","formulaType":1,"maxMatchCount":0,"poolCode":"HAD"},{"fValue":1,"formula":"6x15","formulaType":1,"maxMatchCount":0,"poolCode":"HAD"},{"fValue":1,"formula":"6x20","formulaType":1,"maxMatchCount":0,"poolCode":"HAD"},{"fValue":1,"formula":"6x22","formulaType":1,"maxMatchCount":0,"poolCode":"HAD"},{"fValue":1,"formula":"6x35","formulaType":1,"maxMatchCount":0,"poolCode":"HAD"},{"fValue":1,"formula":"6x42","formulaType":1,"maxMatchCount":0,"poolCode":"HAD"},{"fValue":1,"formula":"6x50","formulaType":1,"maxMatchCount":0,"poolCode":"HAD"},{"fValue":1,"formula":"6x57","formulaType":1,"maxMatchCount":0,"poolCode":"HAD"},{"fValue":1,"formula":"7x1","formulaType":1,"maxMatchCount":0,"poolCode":"HAD"},{"fValue":1,"formula":"7x7","formulaType":1,"maxMatchCount":0,"poolCode":"HAD"},{"fValue":1,"formula":"7x8","formulaType":1,"maxMatchCount":0,"poolCode":"HAD"},{"fValue":1,"formula":"7x21","formulaType":1,"maxMatchCount":0,"poolCode":"HAD"},{"fValue":1,"formula":"7x35","formulaType":1,"maxMatchCount":0,"poolCode":"HAD"},{"fValue":1,"formula":"7x120","formulaType":1,"maxMatchCount":0,"poolCode":"HAD"},{"fValue":1,"formula":"8x1","formulaType":1,"maxMatchCount":0,"poolCode":"HAD"},{"fValue":1,"formula":"8x8","formulaType":1,"maxMatchCount":0,"poolCode":"HAD"},{"fValue":1,"formula":"8x9","formulaType":1,"maxMatchCount":0,"poolCode":"HAD"},{"fValue":1,"formula":"8x28","formulaType":1,"maxMatchCount":0,"poolCode":"HAD"},{"fValue":1,"formula":"8x56","formulaType":1,"maxMatchCount":0,"poolCode":"HAD"},{"fValue":1,"formula":"8x70","formulaType":1,"maxMatchCount":0,"poolCode":"HAD"},{"fValue":1,"formula":"8x247","formulaType":1,"maxMatchCount":0,"poolCode":"HAD"},{"fValue":1,"formula":"Single","formulaType":1,"maxMatchCount":0,"poolCode":"HAD"},{"fValue":1,"formula":"2x1","formulaType":2,"maxMatchCount":0,"poolCode":"HAD"},{"fValue":1,"formula":"3x1","formulaType":2,"maxMatchCount":0,"poolCode":"HAD"},{"fValue":1,"formula":"4x1","formulaType":2,"maxMatchCount":0,"poolCode":"HAD"},{"fValue":1,"formula":"5x1","formulaType":2,"maxMatchCount":0,"poolCode":"HAD"},{"fValue":1,"formula":"6x1","formulaType":2,"maxMatchCount":0,"poolCode":"HAD"},{"fValue":1,"formula":"7x1","formulaType":2,"maxMatchCount":0,"poolCode":"HAD"},{"fValue":1,"formula":"8x1","formulaType":2,"maxMatchCount":0,"poolCode":"HAD"},{"fValue":1,"formula":"Single","formulaType":2,"maxMatchCount":0,"poolCode":"HAD"}]},"leagueList":[{"leagueId":"39","leagueName":"国际赛","leagueNameAbbr":"国际赛"},{"leagueId":"42","leagueName":"日本职业联赛","leagueNameAbbr":"日职"}],"totalCount":10,"lastUpdateTime":"2026-06-05 17:18:07"}}